simple_models-0.6.2.dist-info/DESCRIPTION.rst
simple_models-0.6.2.dist-info/METADATA
simple_models-0.6.2.dist-info/RECORD
simple_models-0.6.2.dist-info/WHEEL
simple_models-0.6.2.dist-info/metadata.json
simple_models-0.6.2.dist-info/top_level.txt
simplemodels/__init__.py
simplemodels/exceptions.py
simplemodels/fields.py
simplemodels/models.py
simplemodels/utils.py
