Metadata-Version: 2.0
Name: simple-models
Version: 0.6.2
Summary: Library for building declarative dict-like structures to get more power and safety in your API applications
Home-page: https://github.com/prawn-cake/simple-models
Author: Maksim Ekimovskii
Author-email: ekimovsky.maksim@gmail.com
License: MIT
Platform: UNKNOWN
Classifier: Intended Audience :: Developers
Classifier: Programming Language :: Python :: 2.7
Classifier: Programming Language :: Python :: 3.4
Requires-Dist: six
